{"teams":[{"id":9565,"name":"Vitality","logo":"https://img-cdn.hltv.org/teamlogo/ogcHrcCdzRvxbYvAz04KAN.png?ixlib=java-2.1.0&w=50&s=e1f6019aa9f274ffe45a5e99c88dbc02","instagram":"https://www.instagram.com/teamvitality","country":{"name":"Europe","code":"EU"},"rank":1,"players":[{"name":"apEX","id":7322,"timeOnTeam":"7 years5 months","mapsPlayed":1384,"type":"Starter"},{"name":"ZywOo","id":11893,"timeOnTeam":"7 years5 months","mapsPlayed":1387,"type":"Starter"},{"name":"flameZ","id":16693,"timeOnTeam":"2 years9 months","mapsPlayed":446,"type":"Starter"},{"name":"mezii","id":18462,"timeOnTeam":"2 years4 months","mapsPlayed":393,"type":"Starter"},{"name":"ropz","id":11816,"timeOnTeam":"1 year2 months","mapsPlayed":240,"type":"Starter"},{"id":9086,"name":"XTQZZZ","timeOnTeam":"2 years5 months","mapsPlayed":407,"type":"Coach"}],"rankingDevelopment":[2,2,2,2,2,2,2,2,1,1,1,1,1,1,1,1,1,3,3,5,5,5,2,2,2,1,1,1,1,1,1,1,1,2,2,2,2,3,3,3,4,3,6,6,6,6,3,4,3,3,2,2,2,2,2,2,4,4,4,3,1,2,2,2,1,2,3,3,3,3,3,3,3,3,3,3,3,4,4,5,4,6,4,4,4,2,2,2,2,2,2,2,1,1,1,1,1,1,1,1,1,1,1,1,1,1,1,1,1,1,1,1,1,1,1,1,1,1,2,2,1,1,1,1,1,1,2,2,2,1,1,1,1,1,1,1,1,1,1,1,1,1,1]},{"id":4608,"name":"Natus Vincere","logo":"https://img-cdn.hltv.org/teamlogo/9iMirAi7ArBLNU8p3kqUTZ.svg?ixlib=java-2.1.0&s=4dd8635be16122656093ae9884675d0c","instagram":"https://www.instagram.com/natus_vincere_official","country":{"name":"Europe","code":"EU"},"rank":2,"players":[{"name":"b1t","id":18987,"timeOnTeam":"5 years2 months","mapsPlayed":817,"type":"Starter"},{"name":"Aleksib","id":9816,"timeOnTeam":"2 years8 months","mapsPlayed":454,"type":"Starter"},{"name":"iM","id":14759,"timeOnTeam":"2 years8 months","mapsPlayed":454,"type":"Starter"},{"name":"w0nderful","id":20127,"timeOnTeam":"2 years4 months","mapsPlayed":406,"type":"Starter"},{"name":"makazze","id":22673,"timeOnTeam":"8 months","mapsPlayed":147,"type":"Starter"},{"name":"jL","id":19206,"timeOnTeam":"2 years8 months","mapsPlayed":307,"type":"Benched"},{"id":472,"name":"B1ad3","timeOnTeam":"6 years6 months","mapsPlayed":1100,"type":"Coach"}],"rankingDevelopment":[30,15,16,9,9,9,9,9,9,8,7,6,5,5,6,6,7,8,8,8,8,8,4,4,4,4,4,4,3,3,6,6,5,6,6,6,6,2,2,2,2,2,2,4,3,4,6,6,5,5,5,5,5,1,1,1,1,2,1,1,1,2,1,1,1,1,1,1,1,1,1,1,1,2,3,3,3,3,3,3,3,3,3,3,3,3,3,3,3,4,5,5,5,4,5,6,7,7,7,7,7,6,6,6,7,7,9,5,5,5,6,7,9,9,9,9,9,9,8,7,8,9,9,9,7,7,8,7,7,7,7,7,7,8,8,8,8,8,9,6,5]}],"players":[{"name":"Vitality","player1":{"id":7322,"name":"Dan Madesclaire","ign":"apEX","image":"https://img-cdn.hltv.org/playerbodyshot/3M9h08qvl3YOsaRcAvKhs4.png?ixlib=java-2.1.0&w=400&s=c1acc9777d9e3165140548582e9bf1f5","age":33,"twitch":"https://www.twitch.tv/apEX","instagram":"https://www.instagram.com/apexcsgo","country":{"name":"France","code":"FR"},"team":{"name":"LinkVitality"},"statistics":{"rating":1,"killsPerRound":null,"headshots":null,"mapsPlayed":null,"deathsPerRound":null,"roundsContributed":null},"achievements":[{"place":"1st","event":{"name":"StarLadder Budapest Major 2025","id":8042}},{"place":"1st","event":{"name":"BLAST.tv Austin Major 2025","id":7902}},{"place":"1/4 final","event":{"name":"Perfect World Shanghai Major 2024","id":7524}},{"place":"3-4th","event":{"name":"PGL CS2 Major Copenhagen 2024","id":7148}},{"place":"1st","event":{"name":"BLAST.tv Paris Major 2023","id":6793}},{"place":"Legends","event":{"name":"IEM Rio Major 2022","id":6586}},{"place":"Legends","event":{"name":"PGL Major Antwerp 2022","id":6372}},{"place":"1/4 final","event":{"name":"PGL Major Stockholm 2021","id":4866}},{"place":"1/4 final","event":{"name":"StarLadder Major Berlin 2019","id":4443}},{"place":"Legends","event":{"name":"IEM Katowice 2019","id":3883}},{"place":"1/4 final","event":{"name":"ELEAGUE Major 2018","id":3247}},{"place":"Group stage","event":{"name":"PGL Major Krakow 2017","id":2720}},{"place":"Group stage","event":{"name":"ELEAGUE Major 2017","id":2471}},{"place":"Group stage","event":{"name":"ESL One Cologne 2016","id":2062}},{"place":"Group stage","event":{"name":"MLG Columbus 2016","id":2027}},{"place":"1st","event":{"name":"DreamHack Open Cluj-Napoca 2015","id":1617}},{"place":"2nd","event":{"name":"ESL One Cologne 2015","id":1666}},{"place":"Group stage","event":{"name":"ESL One Katowice 2015","id":1611}},{"place":"3-4th","event":{"name":"ESL One Cologne 2014","id":1444}},{"place":"1/4 final","event":{"name":"EMS One Katowice 2014","id":1333}},{"place":"Group stage","event":{"name":"DreamHack Winter 2013","id":1270}},{"place":"1st","event":{"name":"PGL Cluj-Napoca 2026","id":8047}},{"place":"1st","event":{"name":"IEM Kraków 2026","id":8240}},{"place":"3-4th","event":{"name":"BLAST Bounty 2026 Season 1 Finals","id":8246}},{"place":"1st","event":{"name":"StarLadder Budapest Major 2025","id":8042}},{"place":"3-4th","event":{"name":"BLAST Rivals 2025 Season 2","id":7908}},{"place":"2nd","event":{"name":"IEM Chengdu 2025","id":8041}},{"place":"1st","event":{"name":"ESL Pro League Season 22","id":8040}},{"place":"2nd","event":{"name":"BLAST Open London 2025 Finals","id":7912}},{"place":"3-4th","event":{"name":"BLAST Bounty 2025 Season 2 Finals","id":7910}},{"place":"3-4th","event":{"name":"IEM Cologne 2025","id":8038}},{"place":"1st","event":{"name":"BLAST.tv Austin Major 2025","id":7902}},{"place":"1st","event":{"name":"IEM Dallas 2025","id":8037}},{"place":"1st","event":{"name":"BLAST Rivals 2025 Season 1","id":7905}},{"place":"1st","event":{"name":"IEM Melbourne 2025","id":8036}},{"place":"1st","event":{"name":"BLAST Open Lisbon 2025","id":7904}},{"place":"1st","event":{"name":"ESL Pro League Season 21","id":8292}},{"place":"1st","event":{"name":"IEM Katowice 2025","id":8034}},{"place":"3-4th","event":{"name":"BLAST Premier World Final 2024","id":7557}},{"place":"3-4th","event":{"name":"BLAST Premier Fall Final 2024","id":7556}},{"place":"1st","event":{"name":"IEM Cologne 2024","id":7436}},{"place":"3-4th","event":{"name":"BLAST Premier Spring Final 2024","id":7485}},{"place":"2nd","event":{"name":"IEM Dallas 2024","id":7438}},{"place":"2nd","event":{"name":"ESL Pro League Season 19","id":7440}},{"place":"3-4th","event":{"name":"PGL CS2 Major Copenhagen 2024","id":7148}},{"place":"1st","event":{"name":"BLAST Premier World Final 2023","id":6976}},{"place":"1st","event":{"name":"BLAST Premier Fall Final 2023","id":6975}},{"place":"1st","event":{"name":"Gamers8 2023","id":7128}},{"place":"3-4th","event":{"name":"IEM Cologne 2023","id":6811}},{"place":"2nd","event":{"name":"BLAST Premier Spring Final 2023","id":6972}},{"place":"1st","event":{"name":"BLAST.tv Paris Major 2023","id":6793}},{"place":"1st","event":{"name":"IEM Rio 2023","id":6864}},{"place":"1st","event":{"name":"ESL Pro League Season 16","id":6141}},{"place":"2nd","event":{"name":"BLAST Premier Spring Final 2022","id":6345}},{"place":"3rd","event":{"name":"BLAST Premier World Final 2021","id":5608}},{"place":"1st","event":{"name":"IEM Winter 2021","id":5730}},{"place":"2nd","event":{"name":"BLAST Premier Fall Final 2021","id":5607}},{"place":"3rd","event":{"name":"IEM Fall 2021 Europe","id":5729}},{"place":"1st","event":{"name":"EPICENTER 2019","id":4979}},{"place":"3-4th","event":{"name":"IEM Beijing 2019","id":4837}},{"place":"2nd","event":{"name":"DreamHack Masters Malmö 2019","id":4553}},{"place":"3-4th","event":{"name":"IEM Chicago 2019","id":4574}},{"place":"2nd","event":{"name":"ESL One Cologne 2019","id":4281}},{"place":"1st","event":{"name":"ECS Season 7 Finals","id":4411}},{"place":"1st","event":{"name":"cs_summit 4","id":4566}},{"place":"3rd","event":{"name":"EPICENTER 2017","id":3133}},{"place":"1st","event":{"name":"DreamHack Masters Malmö 2017","id":2684}},{"place":"1st","event":{"name":"ESL Pro League Season 5 Finals","id":2557}},{"place":"1st","event":{"name":"DreamHack Open Tours 2017","id":2568}},{"place":"3-4th","event":{"name":"DreamHack Open Austin 2017","id":2567}},{"place":"1st","event":{"name":"WESG 2016 World Finals","id":2564}},{"place":"3-4th","event":{"name":"ECS Season 2 Finals","id":2367}},{"place":"3-4th","event":{"name":"DreamHack ZOWIE Open Bucharest 2016","id":2112}},{"place":"3-4th","event":{"name":"DreamHack Masters Malmö 2016","id":2099}},{"place":"1st","event":{"name":"Game Show Global eSports Cup 2016 Finals","id":2013}},{"place":"3-4th","event":{"name":"SL i-League StarSeries XIV Finals","id":1978}},{"place":"3-4th","event":{"name":"ESL ESEA Pro League Season 2 Finals","id":1986}},{"place":"1st","event":{"name":"DreamHack Open Cluj-Napoca 2015","id":1617}},{"place":"1st","event":{"name":"Gfinity 2015 Champion of Champions","id":1621}},{"place":"1st","event":{"name":"DreamHack Open London 2015","id":1763}},{"place":"2nd","event":{"name":"ESL One Cologne 2015","id":1666}},{"place":"1st","event":{"name":"IEM Gamescom 2015","id":1861}},{"place":"3-4th","event":{"name":"DreamHack Open Summer 2015","id":1614}},{"place":"3-4th","event":{"name":"Gfinity 2015 Spring Masters 2","id":1619}},{"place":"3rd","event":{"name":"ESEA Invite Season 18 Global Finals","id":1651}},{"place":"2nd","event":{"name":"ESL Pro League Winter 2014/15 Finals","id":1702}},{"place":"2nd","event":{"name":"Inferno Online Pantamera Challenge","id":1622}},{"place":"2nd","event":{"name":"ASUS ROG Winter 2015","id":1601}},{"place":"3rd","event":{"name":"SLTV StarSeries XI Finals","id":1516}},{"place":"1st","event":{"name":"DreamHack Stockholm CS:GO Invitational 2014","id":1490}},{"place":"3-4th","event":{"name":"ESL One Cologne 2014","id":1444}},{"place":"1st","event":{"name":"DreamHack Valencia 2014","id":1424}},{"place":"3-4th","event":{"name":"Copenhagen Games 2014","id":1345}},{"place":"1st","event":{"name":"ESWC 2013","id":1249}},{"place":"3-4th","event":{"name":"DreamHack Summer 2013","id":1151}}],"teams":[{"id":9565,"name":"Vitality","startDate":1538949600000,"trophies":[{"id":8047,"name":"PGL Cluj-Napoca 2026"},{"id":8240,"name":"IEM Kraków 2026"},{"id":8042,"name":"StarLadder Budapest Major 2025"},{"id":8040,"name":"ESL Pro League Season 22"},{"id":7902,"name":"BLAST.tv Austin Major 2025"},{"id":8037,"name":"IEM Dallas 2025"},{"id":7905,"name":"BLAST Rivals 2025 Season 1"},{"id":41557,"name":"Winner of ESL Grand Slam Season 5"},{"id":8036,"name":"IEM Melbourne 2025"},{"id":7904,"name":"BLAST Open Lisbon 2025"},{"id":8292,"name":"ESL Pro League Season 21"},{"id":8034,"name":"IEM Katowice 2025"},{"id":7436,"name":"IEM Cologne 2024"},{"id":6976,"name":"BLAST Premier World Final 2023"},{"id":6975,"name":"BLAST Premier Fall Final 2023"},{"id":7128,"name":"Gamers8 2023"},{"id":6793,"name":"BLAST.tv Paris Major 2023"},{"id":6864,"name":"IEM Rio 2023"},{"id":6141,"name":"ESL Pro League Season 16"},{"id":5730,"name":"IEM Winter 2021"},{"id":5209,"name":"BLAST Premier Fall 2020 Finals"},{"id":5524,"name":"IEM Beijing-Haidian 2020 Europe"},{"id":4979,"name":"EPICENTER 2019"},{"id":4411,"name":"ECS Season 7 Finals"},{"id":4566,"name":"cs_summit 4"}]},{"id":5995,"name":"G2","startDate":1486076400000,"leaveDate":1538949600000,"trophies":[{"id":2684,"name":"DreamHack Masters Malmö 2017"},{"id":2557,"name":"ESL Pro League Season 5 Finals"},{"id":2568,"name":"DreamHack Open Tours 2017"}]},{"id":5991,"name":"Envy","startDate":1437343200000,"leaveDate":1486076400000,"trophies":[{"id":2564,"name":"WESG 2016 World Finals"},{"id":2013,"name":"Game Show Global eSports Cup 2016 Finals"},{"id":1617,"name":"DreamHack Open Cluj-Napoca 2015"},{"id":1621,"name":"Gfinity 2015 Champion of Champions"},{"id":1763,"name":"DreamHack Open London 2015"},{"id":1861,"name":"IEM Gamescom 2015"}]},{"id":5284,"name":"Titan","startDate":1409695200000,"leaveDate":1437343200000,"trophies":[{"id":1490,"name":"DreamHack Stockholm CS:GO Invitational 2014"}]},{"id":4674,"name":"LDLC","startDate":1391295600000,"leaveDate":1409695200000,"trophies":[{"id":1424,"name":"DreamHack Valencia 2014"}]},{"id":4948,"name":"Clan-Mystik","startDate":1377208800000,"leaveDate":1391295600000,"trophies":[{"id":1249,"name":"ESWC 2013"}]},{"id":4674,"name":"LDLC","startDate":1358031600000,"leaveDate":1376949600000,"trophies":[]},{"id":4512,"name":"eXtensive","startDate":1349906400000,"leaveDate":1357340400000,"trophies":[]}]},"player2":{"id":11893,"name":"Mathieu Herbaut","ign":"ZywOo","image":"https://img-cdn.hltv.org/playerbodyshot/blnoWFtH8GUJZjhr8H0P4u.png?ixlib=java-2.1.0&w=400&s=dc0fe6bd817ef852f59185ccf6b6c868","age":25,"twitch":"https://www.twitch.tv/cs_zywoo","instagram":"https://www.instagram.com/cs_zywoo","country":{"name":"France","code":"FR"},"team":{"name":"Vitality","id":9565},"statistics":{"rating":1.45,"killsPerRound":null,"headshots":null,"mapsPlayed":null,"deathsPerRound":null,"roundsContributed":null},"achievements":[{"place":"1st","event":{"name":"StarLadder Budapest Major 2025","id":8042}},{"place":"1st","event":{"name":"BLAST.tv Austin Major 2025","id":7902}},{"place":"1/4 final","event":{"name":"Perfect World Shanghai Major 2024","id":7524}},{"place":"3-4th","event":{"name":"PGL CS2 Major Copenhagen 2024","id":7148}},{"place":"1st","event":{"name":"BLAST.tv Paris Major 2023","id":6793}},{"place":"Legends","event":{"name":"IEM Rio Major 2022","id":6586}},{"place":"Legends","event":{"name":"PGL Major Antwerp 2022","id":6372}},{"place":"1/4 final","event":{"name":"PGL Major Stockholm 2021","id":4866}},{"place":"1/4 final","event":{"name":"StarLadder Major Berlin 2019","id":4443}},{"place":"Legends","event":{"name":"IEM Katowice 2019","id":3883}},{"place":"1st","event":{"name":"PGL Cluj-Napoca 2026","id":8047}},{"place":"1st","event":{"name":"IEM Kraków 2026","id":8240}},{"place":"3-4th","event":{"name":"BLAST Bounty 2026 Season 1 Finals","id":8246}},{"place":"1st","event":{"name":"StarLadder Budapest Major 2025","id":8042}},{"place":"3-4th","event":{"name":"BLAST Rivals 2025 Season 2","id":7908}},{"place":"2nd","event":{"name":"IEM Chengdu 2025","id":8041}},{"place":"1st","event":{"name":"ESL Pro League Season 22","id":8040}},{"place":"2nd","event":{"name":"BLAST Open London 2025 Finals","id":7912}},{"place":"3-4th","event":{"name":"BLAST Bounty 2025 Season 2 Finals","id":7910}},{"place":"3-4th","event":{"name":"IEM Cologne 2025","id":8038}},{"place":"1st","event":{"name":"BLAST.tv Austin Major 2025","id":7902}},{"place":"1st","event":{"name":"IEM Dallas 2025","id":8037}},{"place":"1st","event":{"name":"BLAST Rivals 2025 Season 1","id":7905}},{"place":"1st","event":{"name":"IEM Melbourne 2025","id":8036}},{"place":"1st","event":{"name":"BLAST Open Lisbon 2025","id":7904}},{"place":"1st","event":{"name":"ESL Pro League Season 21","id":8292}},{"place":"1st","event":{"name":"IEM Katowice 2025","id":8034}},{"place":"3-4th","event":{"name":"BLAST Premier World Final 2024","id":7557}},{"place":"3-4th","event":{"name":"BLAST Premier Fall Final 2024","id":7556}},{"place":"1st","event":{"name":"IEM Cologne 2024","id":7436}},{"place":"3-4th","event":{"name":"BLAST Premier Spring Final 2024","id":7485}},{"place":"2nd","event":{"name":"IEM Dallas 2024","id":7438}},{"place":"2nd","event":{"name":"ESL Pro League Season 19","id":7440}},{"place":"3-4th","event":{"name":"PGL CS2 Major Copenhagen 2024","id":7148}},{"place":"1st","event":{"name":"BLAST Premier World Final 2023","id":6976}},{"place":"1st","event":{"name":"BLAST Premier Fall Final 2023","id":6975}},{"place":"1st","event":{"name":"Gamers8 2023","id":7128}},{"place":"3-4th","event":{"name":"IEM Cologne 2023","id":6811}},{"place":"2nd","event":{"name":"BLAST Premier Spring Final 2023","id":6972}},{"place":"1st","event":{"name":"BLAST.tv Paris Major 2023","id":6793}},{"place":"1st","event":{"name":"IEM Rio 2023","id":6864}},{"place":"1st","event":{"name":"ESL Pro League Season 16","id":6141}},{"place":"2nd","event":{"name":"BLAST Premier Spring Final 2022","id":6345}},{"place":"3rd","event":{"name":"BLAST Premier World Final 2021","id":5608}},{"place":"1st","event":{"name":"IEM Winter 2021","id":5730}},{"place":"2nd","event":{"name":"BLAST Premier Fall Final 2021","id":5607}},{"place":"3rd","event":{"name":"IEM Fall 2021 Europe","id":5729}},{"place":"1st","event":{"name":"EPICENTER 2019","id":4979}},{"place":"3-4th","event":{"name":"IEM Beijing 2019","id":4837}},{"place":"2nd","event":{"name":"DreamHack Masters Malmö 2019","id":4553}},{"place":"3-4th","event":{"name":"IEM Chicago 2019","id":4574}},{"place":"2nd","event":{"name":"ESL One Cologne 2019","id":4281}},{"place":"1st","event":{"name":"ECS Season 7 Finals","id":4411}},{"place":"1st","event":{"name":"cs_summit 4","id":4566}}],"teams":[{"id":9565,"name":"Vitality","startDate":1539640800000,"trophies":[{"id":8047,"name":"PGL Cluj-Napoca 2026"},{"id":8240,"name":"IEM Kraków 2026"},{"id":8042,"name":"StarLadder Budapest Major 2025"},{"id":8040,"name":"ESL Pro League Season 22"},{"id":7902,"name":"BLAST.tv Austin Major 2025"},{"id":8037,"name":"IEM Dallas 2025"},{"id":7905,"name":"BLAST Rivals 2025 Season 1"},{"id":41557,"name":"Winner of ESL Grand Slam Season 5"},{"id":8036,"name":"IEM Melbourne 2025"},{"id":7904,"name":"BLAST Open Lisbon 2025"},{"id":8292,"name":"ESL Pro League Season 21"},{"id":8034,"name":"IEM Katowice 2025"},{"id":7436,"name":"IEM Cologne 2024"},{"id":6976,"name":"BLAST Premier World Final 2023"},{"id":6975,"name":"BLAST Premier Fall Final 2023"},{"id":7128,"name":"Gamers8 2023"},{"id":6793,"name":"BLAST.tv Paris Major 2023"},{"id":6864,"name":"IEM Rio 2023"},{"id":6141,"name":"ESL Pro League Season 16"},{"id":5730,"name":"IEM Winter 2021"},{"id":5209,"name":"BLAST Premier Fall 2020 Finals"},{"id":5524,"name":"IEM Beijing-Haidian 2020 Europe"},{"id":4979,"name":"EPICENTER 2019"},{"id":4411,"name":"ECS Season 7 Finals"},{"id":4566,"name":"cs_summit 4"}]},{"id":5639,"name":"aAa","startDate":1505167200000,"leaveDate":1536184800000,"trophies":[]},{"id":7649,"name":"WySix","startDate":1488668400000,"leaveDate":1502488800000,"trophies":[]},{"id":6889,"name":"E-Corp","startDate":1484262000000,"leaveDate":1488322800000,"trophies":[]},{"id":6683,"name":"nevermind","startDate":1471644000000,"leaveDate":1481842800000,"trophies":[]}]},"player3":{"id":16693,"name":"Shahar Shushan","ign":"flameZ","image":"https://img-cdn.hltv.org/playerbodyshot/LUQi5dX9boyO0uDadUGht5.png?ixlib=java-2.1.0&w=400&s=1c5c46fe41e79b19a69b479d8abbbb41","age":22,"twitch":"https://www.twitch.tv/flameZcsgo","instagram":"https://www.instagram.com/flameZcsgo","country":{"name":"Israel","code":"IL"},"team":{"name":"LinkVitality"},"statistics":{"rating":1.28,"killsPerRound":null,"headshots":null,"mapsPlayed":null,"deathsPerRound":null,"roundsContributed":null},"achievements":[{"place":"1st","event":{"name":"StarLadder Budapest Major 2025","id":8042}},{"place":"1st","event":{"name":"BLAST.tv Austin Major 2025","id":7902}},{"place":"1/4 final","event":{"name":"Perfect World Shanghai Major 2024","id":7524}},{"place":"3-4th","event":{"name":"PGL CS2 Major Copenhagen 2024","id":7148}},{"place":"Challengers","event":{"name":"BLAST.tv Paris Major 2023 Challengers Stage","id":6794}},{"place":"Challengers","event":{"name":"IEM Rio Major 2022 Challengers Stage","id":6588}},{"place":"1st","event":{"name":"PGL Cluj-Napoca 2026","id":8047}},{"place":"1st","event":{"name":"IEM Kraków 2026","id":8240}},{"place":"3-4th","event":{"name":"BLAST Bounty 2026 Season 1 Finals","id":8246}},{"place":"1st","event":{"name":"StarLadder Budapest Major 2025","id":8042}},{"place":"3-4th","event":{"name":"BLAST Rivals 2025 Season 2","id":7908}},{"place":"2nd","event":{"name":"IEM Chengdu 2025","id":8041}},{"place":"1st","event":{"name":"ESL Pro League Season 22","id":8040}},{"place":"2nd","event":{"name":"BLAST Open London 2025 Finals","id":7912}},{"place":"3-4th","event":{"name":"BLAST Bounty 2025 Season 2 Finals","id":7910}},{"place":"3-4th","event":{"name":"IEM Cologne 2025","id":8038}},{"place":"1st","event":{"name":"BLAST.tv Austin Major 2025","id":7902}},{"place":"1st","event":{"name":"IEM Dallas 2025","id":8037}},{"place":"1st","event":{"name":"BLAST Rivals 2025 Season 1","id":7905}},{"place":"1st","event":{"name":"IEM Melbourne 2025","id":8036}},{"place":"1st","event":{"name":"BLAST Open Lisbon 2025","id":7904}},{"place":"1st","event":{"name":"ESL Pro League Season 21","id":8292}},{"place":"1st","event":{"name":"IEM Katowice 2025","id":8034}},{"place":"3-4th","event":{"name":"BLAST Premier World Final 2024","id":7557}},{"place":"3-4th","event":{"name":"BLAST Premier Fall Final 2024","id":7556}},{"place":"1st","event":{"name":"IEM Cologne 2024","id":7436}},{"place":"3-4th","event":{"name":"BLAST Premier Spring Final 2024","id":7485}},{"place":"2nd","event":{"name":"IEM Dallas 2024","id":7438}},{"place":"2nd","event":{"name":"ESL Pro League Season 19","id":7440}},{"place":"3-4th","event":{"name":"PGL CS2 Major Copenhagen 2024","id":7148}},{"place":"1st","event":{"name":"BLAST Premier World Final 2023","id":6976}},{"place":"1st","event":{"name":"BLAST Premier Fall Final 2023","id":6975}},{"place":"1st","event":{"name":"Gamers8 2023","id":7128}},{"place":"3-4th","event":{"name":"IEM Cologne 2023","id":6811}},{"place":"3-4th","event":{"name":"BLAST Premier World Final 2022","id":6349}},{"place":"3-4th","event":{"name":"BLAST Premier Spring Final 2022","id":6345}}],"teams":[{"id":9565,"name":"Vitality","startDate":1687384800000,"trophies":[{"id":8047,"name":"PGL Cluj-Napoca 2026"},{"id":8240,"name":"IEM Kraków 2026"},{"id":8042,"name":"StarLadder Budapest Major 2025"},{"id":8040,"name":"ESL Pro League Season 22"},{"id":7902,"name":"BLAST.tv Austin Major 2025"},{"id":8037,"name":"IEM Dallas 2025"},{"id":7905,"name":"BLAST Rivals 2025 Season 1"},{"id":41557,"name":"Winner of ESL Grand Slam Season 5"},{"id":8036,"name":"IEM Melbourne 2025"},{"id":7904,"name":"BLAST Open Lisbon 2025"},{"id":8292,"name":"ESL Pro League Season 21"},{"id":8034,"name":"IEM Katowice 2025"},{"id":7436,"name":"IEM Cologne 2024"},{"id":6976,"name":"BLAST Premier World Final 2023"},{"id":6975,"name":"BLAST Premier Fall Final 2023"},{"id":7128,"name":"Gamers8 2023"}]},{"id":10503,"name":"OG","startDate":1617919200000,"leaveDate":1687384800000,"trophies":[]},{"id":7234,"name":"Endpoint","startDate":1600207200000,"leaveDate":1617919200000,"trophies":[]},{"id":5873,"name":"Adaptation","startDate":1585864800000,"leaveDate":1593986400000,"trophies":[]},{"id":10276,"name":"Finest","startDate":1565820000000,"leaveDate":1577746800000,"trophies":[]},{"id":8909,"name":"Aequus","startDate":1534284000000,"leaveDate":1565820000000,"trophies":[]}]},"player4":{"id":18462,"name":"William Merriman","ign":"mezii","image":"https://img-cdn.hltv.org/playerbodyshot/7GVUrVLAQkgnuovRkk5Bxw.png?ixlib=java-2.1.0&w=400&s=00b346853396c35e5889b00be2766c99","age":27,"twitch":"https://www.twitch.tv/kingmezii","instagram":"https://www.instagram.com/kingmezii","country":{"name":"United Kingdom","code":"GB"},"team":{"name":"Vitality","id":9565},"statistics":{"rating":1.05,"killsPerRound":null,"headshots":null,"mapsPlayed":null,"deathsPerRound":null,"roundsContributed":null},"achievements":[{"place":"1st","event":{"name":"StarLadder Budapest Major 2025","id":8042}},{"place":"1st","event":{"name":"BLAST.tv Austin Major 2025","id":7902}},{"place":"1/4 final","event":{"name":"Perfect World Shanghai Major 2024","id":7524}},{"place":"3-4th","event":{"name":"PGL CS2 Major Copenhagen 2024","id":7148}},{"place":"Legends","event":{"name":"BLAST.tv Paris Major 2023","id":6793}},{"place":"1/4 final","event":{"name":"IEM Rio Major 2022","id":6586}},{"place":"1st","event":{"name":"PGL Cluj-Napoca 2026","id":8047}},{"place":"1st","event":{"name":"IEM Kraków 2026","id":8240}},{"place":"3-4th","event":{"name":"BLAST Bounty 2026 Season 1 Finals","id":8246}},{"place":"1st","event":{"name":"StarLadder Budapest Major 2025","id":8042}},{"place":"3-4th","event":{"name":"BLAST Rivals 2025 Season 2","id":7908}},{"place":"2nd","event":{"name":"IEM Chengdu 2025","id":8041}},{"place":"1st","event":{"name":"ESL Pro League Season 22","id":8040}},{"place":"2nd","event":{"name":"BLAST Open London 2025 Finals","id":7912}},{"place":"3-4th","event":{"name":"BLAST Bounty 2025 Season 2 Finals","id":7910}},{"place":"3-4th","event":{"name":"IEM Cologne 2025","id":8038}},{"place":"1st","event":{"name":"BLAST.tv Austin Major 2025","id":7902}},{"place":"1st","event":{"name":"IEM Dallas 2025","id":8037}},{"place":"1st","event":{"name":"BLAST Rivals 2025 Season 1","id":7905}},{"place":"1st","event":{"name":"IEM Melbourne 2025","id":8036}},{"place":"1st","event":{"name":"BLAST Open Lisbon 2025","id":7904}},{"place":"1st","event":{"name":"ESL Pro League Season 21","id":8292}},{"place":"1st","event":{"name":"IEM Katowice 2025","id":8034}},{"place":"3-4th","event":{"name":"BLAST Premier Fall Final 2024","id":7556}},{"place":"1st","event":{"name":"IEM Cologne 2024","id":7436}},{"place":"3-4th","event":{"name":"BLAST Premier Spring Final 2024","id":7485}},{"place":"2nd","event":{"name":"IEM Dallas 2024","id":7438}},{"place":"2nd","event":{"name":"ESL Pro League Season 19","id":7440}},{"place":"3-4th","event":{"name":"PGL CS2 Major Copenhagen 2024","id":7148}},{"place":"1st","event":{"name":"BLAST Premier World Final 2023","id":6976}},{"place":"1st","event":{"name":"BLAST Premier Fall Final 2023","id":6975}}],"teams":[{"id":9565,"name":"Vitality","startDate":1699398000000,"trophies":[{"id":8047,"name":"PGL Cluj-Napoca 2026"},{"id":8240,"name":"IEM Kraków 2026"},{"id":8042,"name":"StarLadder Budapest Major 2025"},{"id":8040,"name":"ESL Pro League Season 22"},{"id":7902,"name":"BLAST.tv Austin Major 2025"},{"id":8037,"name":"IEM Dallas 2025"},{"id":7905,"name":"BLAST Rivals 2025 Season 1"},{"id":41557,"name":"Winner of ESL Grand Slam Season 5"},{"id":8036,"name":"IEM Melbourne 2025"},{"id":7904,"name":"BLAST Open Lisbon 2025"},{"id":8292,"name":"ESL Pro League Season 21"},{"id":8034,"name":"IEM Katowice 2025"},{"id":7436,"name":"IEM Cologne 2024"},{"id":6976,"name":"BLAST Premier World Final 2023"},{"id":6975,"name":"BLAST Premier Fall Final 2023"}]},{"id":4991,"name":"fnatic","startDate":1627941600000,"leaveDate":1698879600000,"trophies":[]},{"id":7234,"name":"Endpoint","startDate":1619042400000,"leaveDate":1627941600000,"trophies":[]},{"id":5752,"name":"Cloud9","startDate":1600466400000,"leaveDate":1619042400000,"trophies":[]},{"id":9928,"name":"GamerLegion","startDate":1594591200000,"leaveDate":1600466400000,"trophies":[]},{"id":8020,"name":"Vexed UK","startDate":1559512800000,"leaveDate":1586901600000,"trophies":[]},{"id":9674,"name":"London","startDate":1551654000000,"leaveDate":1559512800000,"trophies":[]}]},"player5":{"id":11816,"name":"Robin Kool","ign":"ropz","image":"https://img-cdn.hltv.org/playerbodyshot/YQ9kQQ3aop1JZQE9xJ140r.png?ixlib=java-2.1.0&w=400&s=d4c7a00036511e25b4854ba3d3af80ca","age":26,"twitch":"https://www.twitch.tv/ropz","instagram":"https://www.instagram.com/ropzicle","country":{"name":"Estonia","code":"EE"},"team":{"name":"Vitality","id":9565},"statistics":{"rating":1.09,"killsPerRound":null,"headshots":null,"mapsPlayed":null,"deathsPerRound":null,"roundsContributed":null},"achievements":[{"place":"1st","event":{"name":"StarLadder Budapest Major 2025","id":8042}},{"place":"1st","event":{"name":"BLAST.tv Austin Major 2025","id":7902}},{"place":"2nd","event":{"name":"Perfect World Shanghai Major 2024","id":7524}},{"place":"2nd","event":{"name":"PGL CS2 Major Copenhagen 2024","id":7148}},{"place":"1/4 final","event":{"name":"BLAST.tv Paris Major 2023","id":6793}},{"place":"Legends","event":{"name":"IEM Rio Major 2022","id":6586}},{"place":"1st","event":{"name":"PGL Major Antwerp 2022","id":6372}},{"place":"Legends","event":{"name":"PGL Major Stockholm 2021","id":4866}},{"place":"Legends","event":{"name":"StarLadder Major Berlin 2019","id":4443}},{"place":"Legends","event":{"name":"FACEIT Major 2018","id":3564}},{"place":"1/4 final","event":{"name":"ELEAGUE Major 2018","id":3247}},{"place":"Group stage","event":{"name":"PGL Major Krakow 2017","id":2720}},{"place":"1st","event":{"name":"PGL Cluj-Napoca 2026","id":8047}},{"place":"1st","event":{"name":"IEM Kraków 2026","id":8240}},{"place":"3-4th","event":{"name":"BLAST Bounty 2026 Season 1 Finals","id":8246}},{"place":"1st","event":{"name":"StarLadder Budapest Major 2025","id":8042}},{"place":"3-4th","event":{"name":"BLAST Rivals 2025 Season 2","id":7908}},{"place":"2nd","event":{"name":"IEM Chengdu 2025","id":8041}},{"place":"1st","event":{"name":"ESL Pro League Season 22","id":8040}},{"place":"2nd","event":{"name":"BLAST Open London 2025 Finals","id":7912}},{"place":"3-4th","event":{"name":"BLAST Bounty 2025 Season 2 Finals","id":7910}},{"place":"3-4th","event":{"name":"IEM Cologne 2025","id":8038}},{"place":"1st","event":{"name":"BLAST.tv Austin Major 2025","id":7902}},{"place":"1st","event":{"name":"IEM Dallas 2025","id":8037}},{"place":"1st","event":{"name":"BLAST Rivals 2025 Season 1","id":7905}},{"place":"1st","event":{"name":"IEM Melbourne 2025","id":8036}},{"place":"1st","event":{"name":"BLAST Open Lisbon 2025","id":7904}},{"place":"1st","event":{"name":"ESL Pro League Season 21","id":8292}},{"place":"1st","event":{"name":"IEM Katowice 2025","id":8034}},{"place":"2nd","event":{"name":"Perfect World Shanghai Major 2024","id":7524}},{"place":"3-4th","event":{"name":"BLAST Premier Fall Final 2024","id":7556}},{"place":"1st","event":{"name":"IEM Chengdu 2024","id":7437}},{"place":"2nd","event":{"name":"PGL CS2 Major Copenhagen 2024","id":7148}},{"place":"2nd","event":{"name":"IEM Katowice 2024","id":7435}},{"place":"2nd","event":{"name":"BLAST Premier World Final 2023","id":6976}},{"place":"2nd","event":{"name":"BLAST Premier Fall Final 2023","id":6975}},{"place":"1st","event":{"name":"CS Asia Championships 2023","id":7365}},{"place":"1st","event":{"name":"IEM Sydney 2023","id":6865}},{"place":"3-4th","event":{"name":"IEM Dallas 2023","id":6861}},{"place":"1st","event":{"name":"ESL Pro League Season 17","id":6862}},{"place":"3-4th","event":{"name":"BLAST Premier World Final 2022","id":6349}},{"place":"2nd","event":{"name":"BLAST Premier Fall Final 2022","id":6348}},{"place":"1st","event":{"name":"IEM Cologne 2022","id":6140}},{"place":"1st","event":{"name":"PGL Major Antwerp 2022","id":6372}},{"place":"1st","event":{"name":"ESL Pro League Season 15","id":6137}},{"place":"1st","event":{"name":"IEM Katowice 2022","id":6136}},{"place":"1st","event":{"name":"ICE Challenge 2020","id":5147}},{"place":"2nd","event":{"name":"EPICENTER 2019","id":4979}},{"place":"1st","event":{"name":"cs_summit 5","id":4998}},{"place":"1st","event":{"name":"ESL Pro League Season 10 Finals","id":4697}},{"place":"1st","event":{"name":"CS:GO Asia Championships 2019","id":4680}},{"place":"3-4th","event":{"name":"V4 Future Sports Festival 2019","id":4828}},{"place":"3-4th","event":{"name":"ESL Pro League Season 9 Finals","id":4490}},{"place":"3-4th","event":{"name":"ESL Pro League Season 8 Finals","id":3376}},{"place":"1st","event":{"name":"ESL One New York 2018","id":3703}},{"place":"3-4th","event":{"name":"DreamHack Masters Stockholm 2018","id":3389}},{"place":"3-4th","event":{"name":"ELEAGUE CS:GO Premier 2018","id":3515}},{"place":"2nd","event":{"name":"ESL One Belo Horizonte 2018","id":3649}},{"place":"3-4th","event":{"name":"StarSeries i-League Season 5","id":3666}},{"place":"3-4th","event":{"name":"IEM Sydney 2018","id":3530}},{"place":"1st","event":{"name":"V4 Future Sports Festival 2018","id":3494}},{"place":"1st","event":{"name":"StarSeries i-League Season 4","id":3486}},{"place":"2nd","event":{"name":"ECS Season 4 Finals","id":3313}},{"place":"2nd","event":{"name":"DreamHack Open Winter 2017","id":2574}},{"place":"3-4th","event":{"name":"DreamHack Open Denver 2017","id":2573}},{"place":"1st","event":{"name":"ESG Tour Mykonos 2017","id":3061}},{"place":"3-4th","event":{"name":"DreamHack Open Tours 2017","id":2568}}],"teams":[{"id":9565,"name":"Vitality","startDate":1736463600000,"trophies":[{"id":8047,"name":"PGL Cluj-Napoca 2026"},{"id":8240,"name":"IEM Kraków 2026"},{"id":8042,"name":"StarLadder Budapest Major 2025"},{"id":8040,"name":"ESL Pro League Season 22"},{"id":7902,"name":"BLAST.tv Austin Major 2025"},{"id":8037,"name":"IEM Dallas 2025"},{"id":7905,"name":"BLAST Rivals 2025 Season 1"},{"id":41557,"name":"Winner of ESL Grand Slam Season 5"},{"id":8036,"name":"IEM Melbourne 2025"},{"id":7904,"name":"BLAST Open Lisbon 2025"},{"id":8292,"name":"ESL Pro League Season 21"},{"id":8034,"name":"IEM Katowice 2025"}]},{"id":6667,"name":"FaZe","startDate":1641164400000,"leaveDate":1735686000000,"trophies":[{"id":7437,"name":"IEM Chengdu 2024"},{"id":7365,"name":"CS Asia Championships 2023"},{"id":7289,"name":"Thunderpick World Championship 2023"},{"id":6865,"name":"IEM Sydney 2023"},{"id":35865,"name":"Winner of ESL Grand Slam Season 4"},{"id":6862,"name":"ESL Pro League Season 17"},{"id":6140,"name":"IEM Cologne 2022"},{"id":6372,"name":"PGL Major Antwerp 2022"},{"id":6137,"name":"ESL Pro League Season 15"},{"id":6136,"name":"IEM Katowice 2022"}]},{"id":4494,"name":"MOUZ","startDate":1491948000000,"leaveDate":1640732400000,"trophies":[{"id":5864,"name":"Flashpoint 3"},{"id":5147,"name":"ICE Challenge 2020"},{"id":4998,"name":"cs_summit 5"},{"id":4697,"name":"ESL Pro League Season 10 Finals"},{"id":4680,"name":"CS:GO Asia Championships 2019"},{"id":3703,"name":"ESL One New York 2018"},{"id":3494,"name":"V4 Future Sports Festival 2018"},{"id":3486,"name":"StarSeries i-League Season 4"},{"id":3061,"name":"ESG Tour Mykonos 2017"}]}]}},{"name":"Natus Vincere","player1":{"id":18987,"name":"Valeriy Vakhovskiy","ign":"b1t","image":"https://img-cdn.hltv.org/playerbodyshot/9qh2YbZOLfeIAPCYfgxAd3.png?ixlib=java-2.1.0&w=400&s=cef57317978ef255ee2c48e322c25560","age":23,"twitch":"https://www.twitch.tv/b1tcs","instagram":"https://www.instagram.com/b1tcsgo","country":{"name":"Ukraine","code":"UA"},"team":{"name":"Natus Vincere","id":4608},"statistics":{"rating":1.09,"killsPerRound":null,"headshots":null,"mapsPlayed":null,"deathsPerRound":null,"roundsContributed":null},"achievements":[{"place":"3-4th","event":{"name":"StarLadder Budapest Major 2025","id":8042}},{"place":"1/4 final","event":{"name":"BLAST.tv Austin Major 2025","id":7902}},{"place":"Legends","event":{"name":"Perfect World Shanghai Major 2024","id":7524}},{"place":"1st","event":{"name":"PGL CS2 Major Copenhagen 2024","id":7148}},{"place":"Legends","event":{"name":"BLAST.tv Paris Major 2023","id":6793}},{"place":"1/4 final","event":{"name":"IEM Rio Major 2022","id":6586}},{"place":"2nd","event":{"name":"PGL Major Antwerp 2022","id":6372}},{"place":"1st","event":{"name":"PGL Major Stockholm 2021","id":4866}},{"place":"1st","event":{"name":"ESL Pro League Season 23 Finals","id":8413}},{"place":"3-4th","event":{"name":"StarLadder Budapest Major 2025","id":8042}},{"place":"2nd","event":{"name":"Thunderpick World Championship 2025","id":8067}},{"place":"3-4th","event":{"name":"IEM Cologne 2025","id":8038}},{"place":"3-4th","event":{"name":"IEM Katowice 2025","id":8034}},{"place":"3-4th","event":{"name":"BLAST Bounty 2025 Season 1 Finals","id":7909}},{"place":"1st","event":{"name":"IEM Rio 2024","id":7439}},{"place":"2nd","event":{"name":"BLAST Premier Fall Final 2024","id":7556}},{"place":"1st","event":{"name":"ESL Pro League Season 20","id":7441}},{"place":"2nd","event":{"name":"IEM Cologne 2024","id":7436}},{"place":"1st","event":{"name":"Esports World Cup 2024","id":7732}},{"place":"2nd","event":{"name":"BLAST Premier Spring Final 2024","id":7485}},{"place":"1st","event":{"name":"PGL CS2 Major Copenhagen 2024","id":7148}},{"place":"3-4th","event":{"name":"BLAST Premier World Final 2023","id":6976}},{"place":"2nd","event":{"name":"ESL Pro League Season 18","id":6863}},{"place":"3-4th","event":{"name":"IEM Rio 2023","id":6864}},{"place":"3-4th","event":{"name":"ESL Pro League Season 17","id":6862}},{"place":"3-4th","event":{"name":"IEM Katowice 2023","id":6809}},{"place":"2nd","event":{"name":"IEM Cologne 2022","id":6140}},{"place":"1st","event":{"name":"BLAST Premier Spring Final 2022","id":6345}},{"place":"2nd","event":{"name":"PGL Major Antwerp 2022","id":6372}},{"place":"3-4th","event":{"name":"IEM Katowice 2022","id":6136}},{"place":"1st","event":{"name":"BLAST Premier World Final 2021","id":5608}},{"place":"1st","event":{"name":"BLAST Premier Fall Final 2021","id":5607}},{"place":"1st","event":{"name":"PGL Major Stockholm 2021","id":4866}},{"place":"1st","event":{"name":"IEM Cologne 2021","id":5469}}],"teams":[{"id":4608,"name":"Natus Vincere","startDate":1611010800000,"trophies":[{"id":8413,"name":"ESL Pro League Season 23 Finals"},{"id":7439,"name":"IEM Rio 2024"},{"id":7441,"name":"ESL Pro League Season 20"},{"id":7732,"name":"Esports World Cup 2024"},{"id":7148,"name":"PGL CS2 Major Copenhagen 2024"},{"id":6345,"name":"BLAST Premier Spring Final 2022"},{"id":5608,"name":"BLAST Premier World Final 2021"},{"id":5607,"name":"BLAST Premier Fall Final 2021"},{"id":4866,"name":"PGL Major Stockholm 2021"},{"id":32367,"name":"Winner of ESL Grand Slam Season 3"},{"id":5554,"name":"ESL Pro League Season 14"},{"id":5469,"name":"IEM Cologne 2021"},{"id":5937,"name":"StarLadder CIS RMR 2021"},{"id":5728,"name":"DreamHack Masters Spring 2021"},{"id":5206,"name":"BLAST Premier Global Final 2020"}]},{"id":10371,"name":"NAVI Junior","startDate":1568066400000,"leaveDate":1611010800000,"trophies":[]}]},"player2":{"id":9816,"name":"Aleksi Virolainen","ign":"Aleksib","image":"https://img-cdn.hltv.org/playerbodyshot/7-TvianW79yWk13gdw-Jc5.png?ixlib=java-2.1.0&w=400&s=f94eda5a77f332bc02821e6b845ca207","age":28,"twitch":"https://www.twitch.tv/Aleeksi","instagram":"https://www.instagram.com/aleksivirolainen","country":{"name":"Finland","code":"FI"},"team":{"name":"Natus Vincere","id":4608},"statistics":{"rating":0.88,"killsPerRound":null,"headshots":null,"mapsPlayed":null,"deathsPerRound":null,"roundsContributed":null},"achievements":[{"place":"3-4th","event":{"name":"StarLadder Budapest Major 2025","id":8042}},{"place":"1/4 final","event":{"name":"BLAST.tv Austin Major 2025","id":7902}},{"place":"Legends","event":{"name":"Perfect World Shanghai Major 2024","id":7524}},{"place":"1st","event":{"name":"PGL CS2 Major Copenhagen 2024","id":7148}},{"place":"Legends","event":{"name":"BLAST.tv Paris Major 2023","id":6793}},{"place":"Legends","event":{"name":"IEM Rio Major 2022","id":6586}},{"place":"Legends","event":{"name":"PGL Major Antwerp 2022","id":6372}},{"place":"1/4 final","event":{"name":"StarLadder Major Berlin 2019","id":4443}},{"place":"2nd","event":{"name":"IEM Katowice 2019","id":3883}},{"place":"1st","event":{"name":"ESL Pro League Season 23 Finals","id":8413}},{"place":"3-4th","event":{"name":"StarLadder Budapest Major 2025","id":8042}},{"place":"2nd","event":{"name":"Thunderpick World Championship 2025","id":8067}},{"place":"3-4th","event":{"name":"IEM Cologne 2025","id":8038}},{"place":"3-4th","event":{"name":"IEM Katowice 2025","id":8034}},{"place":"3-4th","event":{"name":"BLAST Bounty 2025 Season 1 Finals","id":7909}},{"place":"1st","event":{"name":"IEM Rio 2024","id":7439}},{"place":"2nd","event":{"name":"BLAST Premier Fall Final 2024","id":7556}},{"place":"1st","event":{"name":"ESL Pro League Season 20","id":7441}},{"place":"2nd","event":{"name":"IEM Cologne 2024","id":7436}},{"place":"1st","event":{"name":"Esports World Cup 2024","id":7732}},{"place":"2nd","event":{"name":"BLAST Premier Spring Final 2024","id":7485}},{"place":"1st","event":{"name":"PGL CS2 Major Copenhagen 2024","id":7148}},{"place":"3-4th","event":{"name":"BLAST Premier World Final 2023","id":6976}},{"place":"2nd","event":{"name":"ESL Pro League Season 18","id":6863}},{"place":"3-4th","event":{"name":"BLAST Premier Fall Final 2022","id":6348}},{"place":"3-4th","event":{"name":"BLAST Premier Spring Final 2022","id":6345}},{"place":"2nd","event":{"name":"IEM Katowice 2022","id":6136}},{"place":"3-4th","event":{"name":"cs_summit 5","id":4998}},{"place":"2nd","event":{"name":"IEM Chicago 2019","id":4574}},{"place":"2nd","event":{"name":"DreamHack Masters Dallas 2019","id":4177}},{"place":"3-4th","event":{"name":"cs_summit 4","id":4566}},{"place":"1st","event":{"name":"BLAST Pro Series Madrid 2019","id":4328}},{"place":"3rd","event":{"name":"BLAST Pro Series São Paulo 2019","id":4326}},{"place":"2nd","event":{"name":"IEM Katowice 2019","id":3883}},{"place":"1st","event":{"name":"StarSeries i-League Season 6","id":3891}}],"teams":[{"id":4608,"name":"Natus Vincere","startDate":1688076000000,"trophies":[{"id":8413,"name":"ESL Pro League Season 23 Finals"},{"id":7439,"name":"IEM Rio 2024"},{"id":7441,"name":"ESL Pro League Season 20"},{"id":7732,"name":"Esports World Cup 2024"},{"id":7148,"name":"PGL CS2 Major Copenhagen 2024"}]},{"id":4411,"name":"Ninjas in Pyjamas","startDate":1662588000000,"leaveDate":1688076000000,"trophies":[]},{"id":5995,"name":"G2","startDate":1642892400000,"leaveDate":1662588000000,"trophies":[]},{"id":10503,"name":"OG","startDate":1575414000000,"leaveDate":1642892400000,"trophies":[]},{"id":4869,"name":"ENCE","startDate":1522792800000,"leaveDate":1575414000000,"trophies":[{"id":4328,"name":"BLAST Pro Series Madrid 2019"},{"id":3891,"name":"StarSeries i-League Season 6"}]},{"id":7865,"name":"HAVU","startDate":1493762400000,"leaveDate":1522447200000,"trophies":[]},{"id":5727,"name":"ENCORE","startDate":1481497200000,"leaveDate":1493762400000,"trophies":[]},{"id":4869,"name":"ENCE","startDate":1472508000000,"leaveDate":1480633200000,"trophies":[]},{"id":4680,"name":"Recursive","startDate":1443304800000,"leaveDate":1453935600000,"trophies":[]}]},"player3":{"id":14759,"name":"Mihai Ivan","ign":"iM","image":"https://img-cdn.hltv.org/playerbodyshot/lWNcoOFOcHF3uIERANZRXh.png?ixlib=java-2.1.0&w=400&s=cd5df4d5e89df8cab0e4a7edd6db0d8b","age":26,"twitch":"https://www.twitch.tv/imecsgo","instagram":"https://www.instagram.com/imihai29","country":{"name":"Romania","code":"RO"},"team":{"name":"Natus Vincere","id":4608},"statistics":{"rating":1.06,"killsPerRound":null,"headshots":null,"mapsPlayed":null,"deathsPerRound":null,"roundsContributed":null},"achievements":[{"place":"3-4th","event":{"name":"StarLadder Budapest Major 2025","id":8042}},{"place":"1/4 final","event":{"name":"BLAST.tv Austin Major 2025","id":7902}},{"place":"Legends","event":{"name":"Perfect World Shanghai Major 2024","id":7524}},{"place":"1st","event":{"name":"PGL CS2 Major Copenhagen 2024","id":7148}},{"place":"2nd","event":{"name":"BLAST.tv Paris Major 2023","id":6793}},{"place":"Challengers","event":{"name":"IEM Rio Major 2022 Challengers Stage","id":6588}},{"place":"1st","event":{"name":"ESL Pro League Season 23 Finals","id":8413}},{"place":"3-4th","event":{"name":"StarLadder Budapest Major 2025","id":8042}},{"place":"2nd","event":{"name":"Thunderpick World Championship 2025","id":8067}},{"place":"3-4th","event":{"name":"IEM Cologne 2025","id":8038}},{"place":"3-4th","event":{"name":"IEM Katowice 2025","id":8034}},{"place":"3-4th","event":{"name":"BLAST Bounty 2025 Season 1 Finals","id":7909}},{"place":"1st","event":{"name":"IEM Rio 2024","id":7439}},{"place":"2nd","event":{"name":"BLAST Premier Fall Final 2024","id":7556}},{"place":"1st","event":{"name":"ESL Pro League Season 20","id":7441}},{"place":"2nd","event":{"name":"IEM Cologne 2024","id":7436}},{"place":"1st","event":{"name":"Esports World Cup 2024","id":7732}},{"place":"2nd","event":{"name":"BLAST Premier Spring Final 2024","id":7485}},{"place":"1st","event":{"name":"PGL CS2 Major Copenhagen 2024","id":7148}},{"place":"3-4th","event":{"name":"BLAST Premier World Final 2023","id":6976}},{"place":"2nd","event":{"name":"ESL Pro League Season 18","id":6863}},{"place":"2nd","event":{"name":"BLAST.tv Paris Major 2023","id":6793}}],"teams":[{"id":4608,"name":"Natus Vincere","startDate":1688076000000,"trophies":[{"id":8413,"name":"ESL Pro League Season 23 Finals"},{"id":7439,"name":"IEM Rio 2024"},{"id":7441,"name":"ESL Pro League Season 20"},{"id":7732,"name":"Esports World Cup 2024"},{"id":7148,"name":"PGL CS2 Major Copenhagen 2024"}]},{"id":9928,"name":"GamerLegion","startDate":1618437600000,"leaveDate":1688076000000,"trophies":[]},{"id":7187,"name":"Nexus","startDate":1550703600000,"leaveDate":1618437600000,"trophies":[]},{"id":7187,"name":"Nexus","startDate":1516230000000,"leaveDate":1531432800000,"trophies":[]}]},"player4":{"id":20127,"name":"Ihor Zhdanov","ign":"w0nderful","image":"https://img-cdn.hltv.org/playerbodyshot/OepRRBoc68iVojIfgK3JIA.png?ixlib=java-2.1.0&w=400&s=99dcc1115ffec1ed275a5cf4eacca825","age":21,"twitch":"https://www.twitch.tv/w0nderfulof","instagram":"https://www.instagram.com/w0nderfulof","country":{"name":"Ukraine","code":"UA"},"team":{"name":"Natus Vincere","id":4608},"statistics":{"rating":1.04,"killsPerRound":null,"headshots":null,"mapsPlayed":null,"deathsPerRound":null,"roundsContributed":null},"achievements":[{"place":"3-4th","event":{"name":"StarLadder Budapest Major 2025","id":8042}},{"place":"1/4 final","event":{"name":"BLAST.tv Austin Major 2025","id":7902}},{"place":"Legends","event":{"name":"Perfect World Shanghai Major 2024","id":7524}},{"place":"1st","event":{"name":"PGL CS2 Major Copenhagen 2024","id":7148}},{"place":"1/4 final","event":{"name":"IEM Rio Major 2022","id":6586}},{"place":"1st","event":{"name":"ESL Pro League Season 23 Finals","id":8413}},{"place":"3-4th","event":{"name":"StarLadder Budapest Major 2025","id":8042}},{"place":"2nd","event":{"name":"Thunderpick World Championship 2025","id":8067}},{"place":"3-4th","event":{"name":"IEM Cologne 2025","id":8038}},{"place":"3-4th","event":{"name":"IEM Katowice 2025","id":8034}},{"place":"3-4th","event":{"name":"BLAST Bounty 2025 Season 1 Finals","id":7909}},{"place":"1st","event":{"name":"IEM Rio 2024","id":7439}},{"place":"2nd","event":{"name":"BLAST Premier Fall Final 2024","id":7556}},{"place":"1st","event":{"name":"ESL Pro League Season 20","id":7441}},{"place":"2nd","event":{"name":"IEM Cologne 2024","id":7436}},{"place":"1st","event":{"name":"Esports World Cup 2024","id":7732}},{"place":"2nd","event":{"name":"BLAST Premier Spring Final 2024","id":7485}},{"place":"1st","event":{"name":"PGL CS2 Major Copenhagen 2024","id":7148}},{"place":"3-4th","event":{"name":"BLAST Premier World Final 2023","id":6976}}],"teams":[{"id":4608,"name":"Natus Vincere","startDate":1698706800000,"trophies":[{"id":8413,"name":"ESL Pro League Season 23 Finals"},{"id":7439,"name":"IEM Rio 2024"},{"id":7441,"name":"ESL Pro League Season 20"},{"id":7732,"name":"Esports World Cup 2024"},{"id":7148,"name":"PGL CS2 Major Copenhagen 2024"}]},{"id":8637,"name":"Sprout","startDate":1688940000000,"leaveDate":1698706800000,"trophies":[]},{"id":7020,"name":"Spirit","startDate":1655762400000,"leaveDate":1688940000000,"trophies":[]},{"id":5310,"name":"HellRaisers","startDate":1638918000000,"leaveDate":1646175600000,"trophies":[]},{"id":9184,"name":"Gucci Squad","startDate":1638313200000,"leaveDate":1638918000000,"trophies":[]},{"id":11079,"name":"Trasko","startDate":1615762800000,"leaveDate":1636498800000,"trophies":[]},{"id":10473,"name":"Project X","startDate":1608246000000,"leaveDate":1615762800000,"trophies":[]},{"id":9673,"name":"MAJESTY","startDate":1597528800000,"leaveDate":1606863600000,"trophies":[]}]},"player5":{"id":22673,"name":"Drin Shaqiri","ign":"makazze","image":"https://img-cdn.hltv.org/playerbodyshot/U6KmIKHcqg2OpMrNn-Aqk6.png?ixlib=java-2.1.0&w=400&s=420f1bcb0e6943b68fafb5e2d933197c","age":19,"instagram":"https://www.instagram.com/_drinshaqirii","country":{"name":"Kosovo","code":"XK"},"team":{"name":"Natus Vincere","id":4608},"statistics":{"rating":1.18,"killsPerRound":null,"headshots":null,"mapsPlayed":null,"deathsPerRound":null,"roundsContributed":null},"achievements":[{"place":"3-4th","event":{"name":"StarLadder Budapest Major 2025","id":8042}},{"place":"1st","event":{"name":"ESL Pro League Season 23 Finals","id":8413}},{"place":"3-4th","event":{"name":"StarLadder Budapest Major 2025","id":8042}},{"place":"2nd","event":{"name":"Thunderpick World Championship 2025","id":8067}},{"place":"3-4th","event":{"name":"IEM Cologne 2025","id":8038}}],"teams":[{"id":4608,"name":"Natus Vincere","startDate":1751234400000,"trophies":[{"id":8413,"name":"ESL Pro League Season 23 Finals"}]},{"id":10371,"name":"NAVI Junior","startDate":1697320800000,"leaveDate":1751234400000,"trophies":[]},{"id":12255,"name":"KS","startDate":1683496800000,"leaveDate":1693692000000,"trophies":[]}]}}]}